hw/__init__.py
hw/hello.py
uwectsshw-0.0.2.dist-info/METADATA
uwectsshw-0.0.2.dist-info/WHEEL
uwectsshw-0.0.2.dist-info/top_level.txt
uwectsshw-0.0.2.dist-info/RECORD
